MANIFEST.in
setup.py
OUtils/__init__.py
OUtils.egg-info/PKG-INFO
OUtils.egg-info/SOURCES.txt
OUtils.egg-info/dependency_links.txt
OUtils.egg-info/requires.txt
OUtils.egg-info/top_level.txt
OUtils/Kafka/__init__.py
OUtils/Kafka/checks/Heartbeat.py
OUtils/Kafka/checks/__init__.py
OUtils/Kafka/metrics/__init__.py
OUtils/Kafka/operations/RollingRestart.py
OUtils/Kafka/operations/__init__.py
OUtils/configurations/__init__.py
OUtils/configurations/configurationSchema.json